qmad/__init__.py
qmad/ansatz.py
qmad/ansatzVect.py
qmad/effh.py
qmad/solver.py
qmad-1.1.0.dist-info/LICENSE
qmad-1.1.0.dist-info/METADATA
qmad-1.1.0.dist-info/WHEEL
qmad-1.1.0.dist-info/top_level.txt
qmad-1.1.0.dist-info/RECORD
